{
    "prefer_ikea": true,
    "prefer_electrical": true,
    "prefer_internet": true,
    "min_hourly_rate": 79,
    "prefer_urgent": true,
    "max_jobs_weekday": {
        "0": 3,
        "1": 3,
        "2": 2,
        "3": 3,
        "4": 2,
        "5": 2,
        "6": 3
    },
    "prefer_amsterdam": true,
    "max_distance_without_permission": 20,
    "travel_time_between_jobs": 60,
    "notification_methods": {
        "telegram": false,
        "pushbullet": false,
        "email": true,
        "pushover": true,
        "safari_web_push": true
    },
    "telegram": {
        "bot_token": "",
        "chat_id": ""
    },
    "pushbullet": {
        "api_key": ""
    }
}